{
  "inputXml": "Y:/(17) 2026 HYTEK PROJECTS/CORAL HOMES/HG260023 LOT 1165 (69) ATTENBOROUGH DRIVE BANYA/03 DETAILING/03 FRAMECAD DETAILER/01 XML OUTPUT/HG260023 LOT 1165 (69) ATTENBOROUGH DRIVE BANYA-GF-TIN-70.115.xml",
  "reference": "Y:/(17) 2026 HYTEK PROJECTS/CORAL HOMES/HG260023 LOT 1165 (69) ATTENBOROUGH DRIVE BANYA/06 MANUFACTURING/04 ROLLFORMER FILES/Split_HG260023/HG260023_GF-TIN-70.115.rfy",
  "generated": "2026-05-10T05:51:50.316Z",
  "setup": {
    "id": "2",
    "name": "F325iT 70mm"
  },
  "totals": {
    "ours": 164,
    "ref": 164,
    "matched": 164,
    "missing": 0,
    "extras": 0
  },
  "byFrame": []
}